storyteller/__init__.py
storyteller/cli.py
storyteller/metadata.yaml
storyteller/assets/style.css
storyteller/mintilo_ai_app/__init__.py
storyteller/mintilo_ai_app/dqr-deprecated.py
storyteller/mintilo_ai_app/exporter.py
storyteller/mintilo_ai_app/mapping_sheet.py
storyteller/mintilo_ai_app/processor.py
storyteller/mintilo_ai_app/test_runner.py
storyteller/templates/pages/about.html
storyteller_dhs-0.1.3.dist-info/LICENSE
storyteller_dhs-0.1.3.dist-info/METADATA
storyteller_dhs-0.1.3.dist-info/WHEEL
storyteller_dhs-0.1.3.dist-info/entry_points.txt
storyteller_dhs-0.1.3.dist-info/top_level.txt
storyteller_dhs-0.1.3.dist-info/RECORD
