Metadata-Version: 2.1
Name: storyteller-dhs
Version: 0.1.3
Summary: Storyteller-DHS: Explore and analyze DHS (Demographic and Health Surveys) datasets with an intuitive interface and CLI tools.
Home-page: https://github.com/kofiyatech/storyteller-DHS-database-viewer
Author: kofiyatech
Author-email: kofiya.technologies@gmail.com
Keywords: dhs,storyteller,datasette,demographics,health,survey,analysis
Classifier: Development Status :: 3 - Alpha
Classifier: Intended Audience :: Science/Research
Classifier: License :: OSI Approved :: MIT License
Classifier: Programming Language :: Python :: 3
Classifier: Programming Language :: Python :: 3.8
Classifier: Programming Language :: Python :: 3.9
Classifier: Programming Language :: Python :: 3.10
Classifier: Programming Language :: Python :: 3.11
Classifier: Topic :: Scientific/Engineering :: Information Analysis
Classifier: Topic :: Database :: Front-Ends
Requires-Python: >=3.8
License-File: LICENSE
Requires-Dist: click
Requires-Dist: datasette
Requires-Dist: sqlite-utils
Requires-Dist: Jinja2
Requires-Dist: pandas
